org

{'POP_TOP': 1, 
'ROT_TWO': 2, 
'ROT_THREE': 3, 
'DUP_TOP': 4, 
'DUP_TOP_TWO': 5, 
'ROT_FOUR': 6, 
'NOP': 9, 
'UNARY_POSITIVE': 10, 
'UNARY_NEGATIVE': 11, 
'UNARY_NOT': 12, 
'UNARY_INVERT': 15, 
'BINARY_MATRIX_MULTIPLY': 16, 
'INPLACE_MATRIX_MULTIPLY': 17, 
'BINARY_POWER': 19, 
'BINARY_MULTIPLY': 20, 
'BINARY_MODULO': 22, 
'BINARY_ADD': 23, 
'BINARY_SUBTRACT': 24, 
'BINARY_SUBSCR': 25, 
'BINARY_FLOOR_DIVIDE': 26, 
'BINARY_TRUE_DIVIDE': 27, 
'INPLACE_FLOOR_DIVIDE': 28, 
'INPLACE_TRUE_DIVIDE': 29, 
'GET_AITER': 50, 
'GET_ANEXT': 51, 
'BEFORE_ASYNC_WITH': 52, 
'BEGIN_FINALLY': 53, 
'END_ASYNC_FOR': 54, 
'INPLACE_ADD': 55, 
'INPLACE_SUBTRACT': 56, 
'INPLACE_MULTIPLY': 57, 
'INPLACE_MODULO': 59, 
'STORE_SUBSCR': 60, 
'DELETE_SUBSCR': 61, 
'BINARY_LSHIFT': 62, 
'BINARY_RSHIFT': 63, 
'BINARY_AND': 64, 
'BINARY_XOR': 65, 
'BINARY_OR': 66, 
'INPLACE_POWER': 67, 
'GET_ITER': 68, 
'GET_YIELD_FROM_ITER': 69, 
'PRINT_EXPR': 70, 
'LOAD_BUILD_CLASS': 71, 
'YIELD_FROM': 72, 
'GET_AWAITABLE': 73, 
'INPLACE_LSHIFT': 75, 
'INPLACE_RSHIFT': 76, 
'INPLACE_AND': 77, 
'INPLACE_XOR': 78, 
'INPLACE_OR': 79, 
'WITH_CLEANUP_START': 81, 
'WITH_CLEANUP_FINISH': 82, 
'RETURN_VALUE': 83, 
'IMPORT_STAR': 84, 
'SETUP_ANNOTATIONS': 85, 
'YIELD_VALUE': 86, 
'POP_BLOCK': 87, 
'END_FINALLY': 88, 
'POP_EXCEPT': 89, 
'STORE_NAME': 90, 
'DELETE_NAME': 91, 
'UNPACK_SEQUENCE': 92, 
'FOR_ITER': 93, 
'UNPACK_EX': 94, 
'STORE_ATTR': 95, 
'DELETE_ATTR': 96, 
'STORE_GLOBAL': 97, 
'DELETE_GLOBAL': 98, 
'LOAD_CONST': 100, 
'LOAD_NAME': 101, 
'BUILD_TUPLE': 102, 
'BUILD_LIST': 103, 
'BUILD_SET': 104, 
'BUILD_MAP': 105, 
'LOAD_ATTR': 106, 
'COMPARE_OP': 107, 
'IMPORT_NAME': 108, 
'IMPORT_FROM': 109, 
'JUMP_FORWARD': 110, 
'JUMP_IF_FALSE_OR_POP': 111, 
'JUMP_IF_TRUE_OR_POP': 112, 
'JUMP_ABSOLUTE': 113, 
'POP_JUMP_IF_FALSE': 114, 
'POP_JUMP_IF_TRUE': 115, 
'LOAD_GLOBAL': 116, 
'SETUP_FINALLY': 122, 
'LOAD_FAST': 124, 
'STORE_FAST': 125, 
'DELETE_FAST': 126, 
'RAISE_VARARGS': 130, 
'CALL_FUNCTION': 131, 
'MAKE_FUNCTION': 132, 
'BUILD_SLICE': 133, 
'LOAD_CLOSURE': 135, 
'LOAD_DEREF': 136, 
'STORE_DEREF': 137, 
'DELETE_DEREF': 138, 
'CALL_FUNCTION_KW': 141, 
'CALL_FUNCTION_EX': 142, 
'SETUP_WITH': 143, 
'LIST_APPEND': 145, 
'SET_ADD': 146, 
'MAP_ADD': 147, 
'LOAD_CLASSDEREF': 148, 
'EXTENDED_ARG': 144, 
'BUILD_LIST_UNPACK': 149, 
'BUILD_MAP_UNPACK': 150, 
'BUILD_MAP_UNPACK_WITH_CALL': 151, 
'BUILD_TUPLE_UNPACK': 152, 
'BUILD_SET_UNPACK': 153, 
'SETUP_ASYNC_WITH': 154, 
'FORMAT_VALUE': 155, 
'BUILD_CONST_KEY_MAP': 156, 
'BUILD_STRING': 157, 
'BUILD_TUPLE_UNPACK_WITH_CALL': 158, 
'LOAD_METHOD': 160, 
'CALL_METHOD': 161, 
'CALL_FINALLY': 162, 
'POP_FINALLY': 163}

used:

[17, 
64, 
89, 
90, 
96, 
97, 
102, 
108, 
109, 
115, 
122, 
124, 
125, 
130, 
131, 
132, 
133, 
135, 
154, 
155]

0x11 17		'BINARY_MATRIX_MULTIPLY': 16
0x40 64		'POP_TOP': 1
0x59 89		
0x5a 90		
0x60 96
0x61 97		'LOAD_CONST': 100
0x66 102		
0x6c 108
0x6d 109
0x73 115
0x7a 122
0x7c 124
0x7d 125	'STORE_NAME': 90, 
0x82 130
0x83 131
0x84 132
0x85 133
0x87 135
0x9a 154
0x9b 155


remapped:

0x1 1
0x2 2
0x3 3
0x4 4
0x5 5
0x6 6
0x9 9:		'ROT_TWO': 2
0xa 10
0xb 11
0xc 12
0xf 15
0x10 16
0x11 17		'BINARY_MATRIX_MULTIPLY': 16
0x13 19
0x14 20
0x16 22
0x17 23
0x18 24
0x19 25
0x1a 26
0x1b 27
0x1c 28
0x1d 29
0x32 50
0x33 51
0x34 52:	'NOP': 9
0x35 53
0x36 54:	'DUP_TOP_TWO': 5
0x37 55
0x38 56:	'ROT_FOUR': 6
0x39 57
0x3b 59
0x3c 60:	'DUP_TOP': 4
0x3d 61
0x3e 62
0x3f 63
0x40 64		'POP_TOP': 1
0x41 65
0x42 66
0x43 67
0x44 68
0x45 69
0x46 70
0x47 71:	'ROT_THREE': 3
0x48 72
0x49 73
0x4b 75
0x4c 76
0x4d 77
0x4e 78
0x4f 79
0x51 81
0x52 82
0x53 83
0x54 84
0x55 85
0x56 86
0x57 87
0x58 88
0x59 89
0x5a 90
0x5b 91
0x5c 92
0x5d 93
0x5e 94
0x5f 95
0x60 96
0x61 97		'LOAD_CONST': 100
0x62 98
0x64 100
0x65 101
0x66 102
0x67 103	'JUMP_IF_FALSE_OR_POP': 111
0x68 104
0x69 105
0x6a 106
0x6b 107
0x6c 108
0x6d 109
0x6e 110
0x6f 111
0x70 112
0x71 113
0x72 114
0x73 115
0x74 116
0x7a 122
0x7c 124
0x7d 125	'STORE_NAME': 90, 
0x7e 126
0x82 130
0x83 131
0x84 132
0x85 133
0x87 135
0x88 136
0x89 137
0x8a 138
0x8d 141
0x8e 142
0x8f 143
0x91 145
0x92 146
0x93 147
0x94 148
0x90 144
0x95 149
0x96 150
0x97 151
0x98 152
0x99 153
0x9a 154
0x9b 155
0x9c 156
0x9d 157	'JUMP_IF_TRUE_OR_POP': 112
0x9e 158
0xa0 160
0xa1 161
0xa2 162	'POP_EXCEPT': 89, 
0xa3 163

{9


